harpia/__init__.cpython-39-x86_64-linux-gnu.so
harpia/__version__.cpython-39-x86_64-linux-gnu.so
harpia/_version.cpython-39-x86_64-linux-gnu.so
harpia/morphology.cpython-39-x86_64-linux-gnu.so
harpia/restoration.cpython-39-x86_64-linux-gnu.so
harpia/segmentation.cpython-39-x86_64-linux-gnu.so
harpia/common/__init__.cpython-39-x86_64-linux-gnu.so
harpia/common/size.cpython-39-x86_64-linux-gnu.so
harpia/distanceTransform/distance_transform_log_sum_kernel.cpython-39-x86_64-linux-gnu.so
harpia/fastGraphClustering/fgc.cpython-39-x86_64-linux-gnu.so
harpia/featureExtraction/__init__.cpython-39-x86_64-linux-gnu.so
harpia/featureExtraction/pixelfeatureExtraction.cpython-39-x86_64-linux-gnu.so
harpia/featureExtraction/superPixelFeatureExtraction.cpython-39-x86_64-linux-gnu.so
harpia/filters/__init__.cpython-39-x86_64-linux-gnu.so
harpia/filters/filtersChunked.cpython-39-x86_64-linux-gnu.so
harpia/filters/filtersOperations.cpython-39-x86_64-linux-gnu.so
harpia/localBinaryPattern/lbp.cpython-39-x86_64-linux-gnu.so
harpia/quantification/quantification.cpython-39-x86_64-linux-gnu.so
harpia/shapeIndex/shape_index.cpython-39-x86_64-linux-gnu.so
harpia/sparseUnmixing/nmf.cpython-39-x86_64-linux-gnu.so
harpia/superpixel/snic.cpython-39-x86_64-linux-gnu.so
harpia/threshold/thresholdChunked.cpython-39-x86_64-linux-gnu.so
harpia/threshold/thresholdOperations.cpython-39-x86_64-linux-gnu.so
harpia/watershed/watershed.cpython-39-x86_64-linux-gnu.so
harpia_sirius-2.7.2.dist-info/LICENSE
harpia_sirius-2.7.2.dist-info/METADATA
harpia_sirius-2.7.2.dist-info/WHEEL
harpia_sirius-2.7.2.dist-info/top_level.txt
harpia_sirius-2.7.2.dist-info/RECORD
