Metadata-Version: 2.1
Name: harpia-sirius
Version: 2.7.2
Summary: CUDA extension for Python
License-File: LICENSE
